wallace/__init__.py
wallace/__init__.pyc
wallace/command_line.py
wallace/command_line.pyc
wallace/custom.py
wallace/db.py
wallace/db.pyc
wallace/experiments.py
wallace/experiments.pyc
wallace/information.py
wallace/information.pyc
wallace/models.py
wallace/models.pyc
wallace/networks.py
wallace/networks.pyc
wallace/nodes.py
wallace/nodes.pyc
wallace/processes.py
wallace/processes.pyc
wallace/recruiters.py
wallace/recruiters.pyc
wallace/transformations.py
wallace/transformations.pyc
wallace/version.py
wallace/version.pyc
wallace/config/.wallaceconfig
wallace/frontend/static/robots.txt
wallace/frontend/static/css/wallace.css
wallace/frontend/static/scripts/reqwest.min.js
wallace/frontend/static/scripts/wallace.js
wallace/frontend/templates/complete.html
wallace/frontend/templates/error_wallace.html
wallace/frontend/templates/launch.html
wallace/heroku/__init__.py
wallace/heroku/clock.py
wallace/heroku/Procfile
wallace/heroku/Procfile_no_clock
wallace/heroku/psiturkapp.py
wallace/heroku/requirements.txt
wallace/heroku/worker.py
wallace_platform-0.12.4.dist-info/dependency_links.txt
wallace_platform-0.12.4.dist-info/DESCRIPTION.rst
wallace_platform-0.12.4.dist-info/entry_points.txt
wallace_platform-0.12.4.dist-info/METADATA
wallace_platform-0.12.4.dist-info/metadata.json
wallace_platform-0.12.4.dist-info/pbr.json
wallace_platform-0.12.4.dist-info/RECORD
wallace_platform-0.12.4.dist-info/top_level.txt
wallace_platform-0.12.4.dist-info/WHEEL
